aiosqlite/__init__.py
aiosqlite/__version__.py
aiosqlite/context.py
aiosqlite/core.py
aiosqlite/cursor.py
aiosqlite/py.typed
aiosqlite/tests/__init__.py
aiosqlite/tests/__main__.py
aiosqlite/tests/helpers.py
aiosqlite/tests/perf.py
aiosqlite/tests/smoke.py
aiosqlite_custom-0.19.0.dist-info/LICENSE
aiosqlite_custom-0.19.0.dist-info/WHEEL
aiosqlite_custom-0.19.0.dist-info/METADATA
aiosqlite_custom-0.19.0.dist-info/RECORD
