Metadata-Version: 2.1
Name: aiosqlite-custom
Version: 0.19.0
Summary: asyncio bridge to the standard sqlite3 module
Author-email: Amethyst Reese <amy@n7.gg>
Requires-Python: >=3.8
Classifier: Development Status :: 5 - Production/Stable
Classifier: Framework :: AsyncIO
Classifier: Intended Audience :: Developers
Classifier: License :: OSI Approved :: MIT License
Classifier: Topic :: Software Development :: Libraries
Requires-Dist: typing_extensions >= 4.0
Requires-Dist: attribution==1.6.2 ; extra == "dev"
Requires-Dist: black==23.3.0 ; extra == "dev"
Requires-Dist: coverage[toml]==7.2.5 ; extra == "dev"
Requires-Dist: flake8==6.0.0 ; extra == "dev"
Requires-Dist: flake8-bugbear==23.3.23 ; extra == "dev"
Requires-Dist: flit==3.8.0 ; extra == "dev"
Requires-Dist: mypy==1.2.0 ; extra == "dev"
Requires-Dist: ufmt==2.1.0 ; extra == "dev"
Requires-Dist: usort==1.0.7 ; extra == "dev"
Requires-Dist: sphinx==7.0.0 ; extra == "docs"
Requires-Dist: sphinx-mdinclude==0.5.3 ; extra == "docs"
Project-URL: Github, https://github.com/bdraco/aiosqlite/tree/speed_up_process_thread
Provides-Extra: dev
Provides-Extra: docs
